[{"id":"6282147334265@s.whatsapp.net","copperingot":null},{"id":"62853893076701@s.whatsapp.net","copperingot":0},{"id":"62888023575290@s.whatsapp.net","copperingot":0},{"id":"6287774719147@s.whatsapp.net","copperingot":0},{"id":"6281314388515@s.whatsapp.net","copperingot":0},{"id":"6288802357529@s.whatsapp.net","copperingot":0},{"id":"6289601489394@s.whatsapp.net","copperingot":0},{"id":"6282135261212@s.whatsapp.net","copperingot":0},{"id":"6285732037924@s.whatsapp.net","copperingot":0},{"id":"6281283632491@s.whatsapp.net","copperingot":0},{"id":"6288287490755@s.whatsapp.net","copperingot":0},{"id":"6281230423770@s.whatsapp.net","copperingot":0},{"id":"6281395770421@s.whatsapp.net","copperingot":0},{"id":"959780991565@s.whatsapp.net","copperingot":7},{"id":"6281326889255@s.whatsapp.net","copperingot":0},{"id":"6281917971050@s.whatsapp.net","copperingot":0},{"id":"6282228279474@s.whatsapp.net","copperingot":0},{"id":"6289506868564@s.whatsapp.net","copperingot":0},{"id":"6288805187479@s.whatsapp.net","copperingot":0},{"id":"6281338982321@s.whatsapp.net","copperingot":0},{"id":"60167884852@s.whatsapp.net","copperingot":0},{"id":"6289515833869@s.whatsapp.net","copperingot":0},{"id":"6282181716596@s.whatsapp.net","copperingot":0},{"id":"6281229765408@s.whatsapp.net","copperingot":0},{"id":"6282341809979@s.whatsapp.net","copperingot":0},{"id":"6285741952658@s.whatsapp.net","copperingot":0},{"id":"6281945742756@s.whatsapp.net","copperingot":0},{"id":"62856438334741@s.whatsapp.net","copperingot":-672},{"id":"6281995141911@s.whatsapp.net","copperingot":0},{"id":"6281802540655@s.whatsapp.net","copperingot":0},{"id":"6281909637189@s.whatsapp.net","copperingot":0},{"id":"6281228699599@s.whatsapp.net","copperingot":0},{"id":"62812297654087@s.whatsapp.net","copperingot":0},{"id":"6281342920552@s.whatsapp.net","copperingot":9},{"id":"6285346104367@s.whatsapp.net","copperingot":0},{"id":"62853461043675@s.whatsapp.net","copperingot":0},{"id":"6282157420156@s.whatsapp.net","copperingot":0},{"id":"62812297654085@s.whatsapp.net","copperingot":0},{"id":"6285876213610@s.whatsapp.net","copperingot":0},{"id":"6283159154029@s.whatsapp.net","copperingot":0},{"id":"6287827674202@s.whatsapp.net","copperingot":0},{"id":"60147141373@s.whatsapp.net","copperingot":0},{"id":"6281228993105@s.whatsapp.net","copperingot":0},{"id":"6282256041442@s.whatsapp.net","copperingot":0},{"id":"6285237673327@s.whatsapp.net","copperingot":0},{"id":"6285921023279@s.whatsapp.net","copperingot":0},{"id":"6281273586443@s.whatsapp.net","copperingot":0},{"id":"62895636922647@s.whatsapp.net","copperingot":0},{"id":"62895349075425@s.whatsapp.net","copperingot":0},{"id":"6289504386265@s.whatsapp.net","copperingot":0},{"id":"6281378140321@s.whatsapp.net","copperingot":0},{"id":"62895340686671@s.whatsapp.net","copperingot":0},{"id":"6281225763093@s.whatsapp.net","copperingot":0},{"id":"628889131213@s.whatsapp.net","copperingot":0},{"id":"6285229281180@s.whatsapp.net","copperingot":0},{"id":"6281326229304@s.whatsapp.net","copperingot":0},{"id":"6282181635983@s.whatsapp.net","copperingot":0},{"id":"628886060342@s.whatsapp.net","copperingot":0},{"id":"601169581342@s.whatsapp.net","copperingot":0},{"id":"6281273135019@s.whatsapp.net","copperingot":0},{"id":"6281296689300@s.whatsapp.net","copperingot":0},{"id":"6285643833474@s.whatsapp.net","copperingot":0},{"id":"6285751586618@s.whatsapp.net","copperingot":0},{"id":"6281238092685@s.whatsapp.net","copperingot":0},{"id":"6285974824930@s.whatsapp.net","copperingot":0},{"id":"62813356579063@s.whatsapp.net","copperingot":0},{"id":"6285925153319@s.whatsapp.net","copperingot":0},{"id":"6282157581762@s.whatsapp.net","copperingot":0},{"id":"6285955322335@s.whatsapp.net","copperingot":0},{"id":"6282134283834@s.whatsapp.net","copperingot":6},{"id":"6283140477003@s.whatsapp.net","copperingot":0},{"id":"6281347258700@s.whatsapp.net","copperingot":0},{"id":"6282345349505@s.whatsapp.net","copperingot":0},{"id":"6282149861801@s.whatsapp.net","copperingot":0},{"id":"6282159536818@s.whatsapp.net","copperingot":6},{"id":"6287739930695@s.whatsapp.net","copperingot":0},{"id":"6282246185469@s.whatsapp.net","copperingot":0},{"id":"6281703441008@s.whatsapp.net","copperingot":0},{"id":"6283149894499@s.whatsapp.net","copperingot":0},{"id":"6282198995591@s.whatsapp.net","copperingot":-999589},{"id":"6282286021019@s.whatsapp.net","copperingot":41},{"id":"6281248519847@s.whatsapp.net","copperingot":8},{"id":"6282187624414@s.whatsapp.net","copperingot":0},{"id":"6283829149523@s.whatsapp.net","copperingot":0},{"id":"6285237723000@s.whatsapp.net","copperingot":11},{"id":"6285745513937@s.whatsapp.net","copperingot":0},{"id":"6287871987625@s.whatsapp.net","copperingot":0},{"id":"62895328768282@s.whatsapp.net","copperingot":0},{"id":"6289696112634@s.whatsapp.net","copperingot":0},{"id":"6285781722351@s.whatsapp.net","copperingot":0},{"id":"62895374696969@s.whatsapp.net","copperingot":0},{"id":"62895639751414@s.whatsapp.net","copperingot":0},{"id":"6285524608356@s.whatsapp.net","copperingot":0},{"id":"6287781495949@s.whatsapp.net","copperingot":0},{"id":"6285888291299@s.whatsapp.net","copperingot":0},{"id":"2348122477293@s.whatsapp.net","copperingot":0},{"id":"3816772229171@s.whatsapp.net","copperingot":0},{"id":"6285959375675@s.whatsapp.net","copperingot":0},{"id":"6285731985795@s.whatsapp.net","copperingot":null},{"id":"6283193310580@s.whatsapp.net","copperingot":0},{"id":"6282326165260@s.whatsapp.net","copperingot":2},{"id":"6285693768044@s.whatsapp.net","copperingot":61},{"id":"6287822888184@s.whatsapp.net","copperingot":-72},{"id":"62881026144286@s.whatsapp.net","copperingot":286},{"id":"6282288311918@s.whatsapp.net","copperingot":101},{"id":"62895602640500@s.whatsapp.net","copperingot":0},{"id":"62881024194468@s.whatsapp.net","copperingot":11},{"id":"6285813195687@s.whatsapp.net","copperingot":-8883701350},{"id":"6282281797190@s.whatsapp.net","copperingot":0},{"id":"6285774383715@s.whatsapp.net","copperingot":0},{"id":"6282348858350@s.whatsapp.net","copperingot":0},{"id":"6287728495363@s.whatsapp.net","copperingot":0},{"id":"6287770552011@s.whatsapp.net","copperingot":2},{"id":"6285730343064@s.whatsapp.net","copperingot":0},{"id":"84582837033@s.whatsapp.net","copperingot":0},{"id":"6287838220598@s.whatsapp.net","copperingot":0},{"id":"6285771736469@s.whatsapp.net","copperingot":0},{"id":"51964243136@s.whatsapp.net","copperingot":0},{"id":"6283823375360@s.whatsapp.net","copperingot":0},{"id":"62895336863845@s.whatsapp.net","copperingot":0},{"id":"6281219700198@s.whatsapp.net","copperingot":0},{"id":"6285334599761@s.whatsapp.net","copperingot":0},{"id":"6285788555068@s.whatsapp.net","copperingot":0},{"id":"6281212369303@s.whatsapp.net","copperingot":49},{"id":"6287728108524@s.whatsapp.net","copperingot":0},{"id":"6289508585962@s.whatsapp.net","copperingot":15},{"id":"628125873899@s.whatsapp.net","copperingot":0},{"id":"6285803357947@s.whatsapp.net","copperingot":0},{"id":"6281111110838@s.whatsapp.net","copperingot":0},{"id":"6283865019527@s.whatsapp.net","copperingot":110},{"id":"60187947418@s.whatsapp.net","copperingot":0},{"id":"62896945935804@s.whatsapp.net","copperingot":0},{"id":"233571482168@s.whatsapp.net","copperingot":0},{"id":"6282115066685@s.whatsapp.net","copperingot":0},{"id":"27634164890@s.whatsapp.net","copperingot":0},{"id":"6282125434640@s.whatsapp.net","copperingot":0},{"id":"6285601612304@s.whatsapp.net","copperingot":0},{"id":"6281270212628@s.whatsapp.net","copperingot":0},{"id":"6281574918506@s.whatsapp.net","copperingot":0},{"id":"6288230229552@s.whatsapp.net","copperingot":0},{"id":"6288232725096@s.whatsapp.net","copperingot":4},{"id":"628875136706@s.whatsapp.net","copperingot":0},{"id":"6283195943836@s.whatsapp.net","copperingot":0},{"id":"6285294774679@s.whatsapp.net","copperingot":0},{"id":"6285733090802@s.whatsapp.net","copperingot":0},{"id":"6282228174890@s.whatsapp.net","copperingot":0},{"id":"6285155345990@s.whatsapp.net","copperingot":0},{"id":"6281372218264@s.whatsapp.net","copperingot":0},{"id":"6285717186084@s.whatsapp.net","copperingot":0},{"id":"60163977244@s.whatsapp.net","copperingot":0},{"id":"6285697924566@s.whatsapp.net","copperingot":16},{"id":"628813281948@s.whatsapp.net","copperingot":0},{"id":"18077009866@s.whatsapp.net","copperingot":0},{"id":"6281999539757@s.whatsapp.net","copperingot":0},{"id":"6287827073935@s.whatsapp.net","copperingot":0},{"id":"6287870399432@s.whatsapp.net","copperingot":0},{"id":"6281212011745@s.whatsapp.net","copperingot":0},{"id":"6285234632936@s.whatsapp.net","copperingot":0},{"id":"6281330544430@s.whatsapp.net","copperingot":0},{"id":"6282268512600@s.whatsapp.net","copperingot":0},{"id":"6285806500191@s.whatsapp.net","copperingot":0},{"id":"62895370957020@s.whatsapp.net","copperingot":0},{"id":"6283803608674@s.whatsapp.net","copperingot":0},{"id":"60147765098@s.whatsapp.net","copperingot":0},{"id":"6285271569265@s.whatsapp.net","copperingot":0},{"id":"33760852030@s.whatsapp.net","copperingot":0},{"id":"6285839864563@s.whatsapp.net","copperingot":0},{"id":"6281717533350@s.whatsapp.net","copperingot":0},{"id":"62895418588118@s.whatsapp.net","copperingot":0},{"id":"6285389461970@s.whatsapp.net","copperingot":0},{"id":"6288289421720@s.whatsapp.net","copperingot":91},{"id":"2349077772709@s.whatsapp.net","copperingot":0},{"id":"6285669055848@s.whatsapp.net","copperingot":0},{"id":"6287809316599@s.whatsapp.net","copperingot":0},{"id":"6281231468806@s.whatsapp.net","copperingot":0},{"id":"6281338400064@s.whatsapp.net","copperingot":0},{"id":"62895384960486@s.whatsapp.net","copperingot":0},{"id":"6285771798901@s.whatsapp.net","copperingot":0},{"id":"6281230405051@s.whatsapp.net","copperingot":0},{"id":"6281332295315@s.whatsapp.net","copperingot":0},{"id":"6285876408741@s.whatsapp.net","copperingot":0},{"id":"6282179910144@s.whatsapp.net","copperingot":0},{"id":"6281222475265@s.whatsapp.net","copperingot":0},{"id":"6281232851052@s.whatsapp.net","copperingot":0},{"id":"6285820835848@s.whatsapp.net","copperingot":0},{"id":"6285747473417@s.whatsapp.net","copperingot":0},{"id":"6282257180754@s.whatsapp.net","copperingot":0},{"id":"6283807973622@s.whatsapp.net","copperingot":0},{"id":"6281803818884@s.whatsapp.net","copperingot":0},{"id":"6287844221072@s.whatsapp.net","copperingot":0},{"id":"6288230122979@s.whatsapp.net","copperingot":0},{"id":"6289694689024@s.whatsapp.net","copperingot":0},{"id":"6288217083679@s.whatsapp.net","copperingot":0},{"id":"62895704620406@s.whatsapp.net","copperingot":0},{"id":"628816951630@s.whatsapp.net","copperingot":0},{"id":"6285280398214@s.whatsapp.net","copperingot":0},{"id":"628119855577@s.whatsapp.net","copperingot":0},{"id":"6287861441262@s.whatsapp.net","copperingot":0},{"id":"6289524912609@s.whatsapp.net","copperingot":0},{"id":"6285242140229@s.whatsapp.net","copperingot":0},{"id":"62895351884700@s.whatsapp.net","copperingot":0},{"id":"6288740071913@s.whatsapp.net","copperingot":0},{"id":"6282345976161@s.whatsapp.net","copperingot":0},{"id":"60165689427@s.whatsapp.net","copperingot":0},{"id":"12264554515@s.whatsapp.net","copperingot":0},{"id":"6289635674356@s.whatsapp.net","copperingot":0},{"id":"6285691951877@s.whatsapp.net","copperingot":0},{"id":"6285850933075@s.whatsapp.net","copperingot":197},{"id":"6288220499534@s.whatsapp.net","copperingot":0},{"id":"6282165480970@s.whatsapp.net","copperingot":0},{"id":"6285732257173@s.whatsapp.net","copperingot":0},{"id":"6289634402727@s.whatsapp.net","copperingot":0},{"id":"628818082272@s.whatsapp.net","copperingot":12},{"id":"6289626824427@s.whatsapp.net","copperingot":0},{"id":"6282120791018@s.whatsapp.net","copperingot":0},{"id":"6281910900055@s.whatsapp.net","copperingot":0},{"id":"6285780259188@s.whatsapp.net","copperingot":0},{"id":"628999310118@s.whatsapp.net","copperingot":48},{"id":"6281545528766@s.whatsapp.net","copperingot":0},{"id":"6281297938773@s.whatsapp.net","copperingot":0},{"id":"60198460513@s.whatsapp.net","copperingot":0},{"id":"6288263759126@s.whatsapp.net","copperingot":0},{"id":"6281283338027@s.whatsapp.net","copperingot":0},{"id":"6282387585240@s.whatsapp.net","copperingot":0},{"id":"6281351432247@s.whatsapp.net","copperingot":0},{"id":"6282318055623@s.whatsapp.net","copperingot":0},{"id":"62895330248557@s.whatsapp.net","copperingot":0},{"id":"6285722016610@s.whatsapp.net","copperingot":0},{"id":"6281240684267@s.whatsapp.net","copperingot":0},{"id":"6285156173307@s.whatsapp.net","copperingot":0},{"id":"6281515596394@s.whatsapp.net","copperingot":0},{"id":"6282314807366@s.whatsapp.net","copperingot":0},{"id":"6282252316014@s.whatsapp.net","copperingot":0},{"id":"6281242262744@s.whatsapp.net","copperingot":0},{"id":"6285817040768@s.whatsapp.net","copperingot":0},{"id":"6285777814412@s.whatsapp.net","copperingot":0},{"id":"6289524430518@s.whatsapp.net","copperingot":0},{"id":"6285777601164@s.whatsapp.net","copperingot":0},{"id":"6281334699633@s.whatsapp.net","copperingot":0},{"id":"6283899975451@s.whatsapp.net","copperingot":0},{"id":"6287888927451@s.whatsapp.net","copperingot":0},{"id":"6285731743550@s.whatsapp.net","copperingot":0},{"id":"6281256585085@s.whatsapp.net","copperingot":0},{"id":"6282260226319@s.whatsapp.net","copperingot":0},{"id":"6281360060436@s.whatsapp.net","copperingot":0},{"id":"6285215172767@s.whatsapp.net","copperingot":0},{"id":"6285754620652@s.whatsapp.net","copperingot":0},{"id":"6282244109938@s.whatsapp.net","copperingot":0},{"id":"6281382767608@s.whatsapp.net","copperingot":0},{"id":"6289527673850@s.whatsapp.net","copperingot":0},{"id":"6285363996723@s.whatsapp.net","copperingot":0},{"id":"6281256623399@s.whatsapp.net","copperingot":0},{"id":"6285368008416@s.whatsapp.net","copperingot":0},{"id":"6285893444409@s.whatsapp.net","copperingot":0},{"id":"60189853704@s.whatsapp.net","copperingot":0},{"id":"6285754207925@s.whatsapp.net","copperingot":3},{"id":"6287777733866@s.whatsapp.net","copperingot":0},{"id":"6281549441920@s.whatsapp.net","copperingot":0},{"id":"62895341787775@s.whatsapp.net","copperingot":0},{"id":"6281232865077@s.whatsapp.net","copperingot":0},{"id":"6287802065203@s.whatsapp.net","copperingot":0},{"id":"6282260701182@s.whatsapp.net","copperingot":0},{"id":"6285892118774@s.whatsapp.net","copperingot":0},{"id":"628111253103@s.whatsapp.net","copperingot":0},{"id":"628111858126@s.whatsapp.net","copperingot":0},{"id":"6285888572008@s.whatsapp.net","copperingot":0},{"id":"6282129599612@s.whatsapp.net","copperingot":0},{"id":"6283845841957@s.whatsapp.net","copperingot":0},{"id":"6281370666190@s.whatsapp.net","copperingot":0},{"id":"6282175184022@s.whatsapp.net","copperingot":0},{"id":"6281317253540@s.whatsapp.net","copperingot":0},{"id":"491625175008@s.whatsapp.net","copperingot":0},{"id":"6283119564271@s.whatsapp.net","copperingot":0},{"id":"6281292675395@s.whatsapp.net","copperingot":476},{"id":"6287703702661@s.whatsapp.net","copperingot":0},{"id":"6282124874081@s.whatsapp.net","copperingot":0},{"id":"6288225856044@s.whatsapp.net","copperingot":0},{"id":"6289652074810@s.whatsapp.net","copperingot":0},{"id":"14703335712@s.whatsapp.net","copperingot":0},{"id":"6281213983935@s.whatsapp.net","copperingot":0},{"id":"6289523333041@s.whatsapp.net","copperingot":0},{"id":"601158785831@s.whatsapp.net","copperingot":0},{"id":"6281928286708@s.whatsapp.net","copperingot":0},{"id":"6285319371043@s.whatsapp.net","copperingot":0},{"id":"6281275419804@s.whatsapp.net","copperingot":0},{"id":"491627430443@s.whatsapp.net","copperingot":0},{"id":"6285348299744@s.whatsapp.net","copperingot":0},{"id":"6281327837286@s.whatsapp.net","copperingot":0},{"id":"6283896371359@s.whatsapp.net","copperingot":0},{"id":"6289517731898@s.whatsapp.net","copperingot":0},{"id":"6285781011070@s.whatsapp.net","copperingot":0},{"id":"6287756662981@s.whatsapp.net","copperingot":0},{"id":"6287726040629@s.whatsapp.net","copperingot":0},{"id":"15632794408@s.whatsapp.net","copperingot":0},{"id":"6281215199447@s.whatsapp.net","copperingot":0},{"id":"60199782326@s.whatsapp.net","copperingot":0},{"id":"6283862829077@s.whatsapp.net","copperingot":0},{"id":"994404396685@s.whatsapp.net","copperingot":0},{"id":"6285717401886@s.whatsapp.net","copperingot":0},{"id":"628981936663@s.whatsapp.net","copperingot":0},{"id":"6285722646504@s.whatsapp.net","copperingot":0},{"id":"6287815252115@s.whatsapp.net","copperingot":0},{"id":"62895334902017@s.whatsapp.net","copperingot":0},{"id":"6285607766451@s.whatsapp.net","copperingot":0},{"id":"6281210891770@s.whatsapp.net","copperingot":0},{"id":"628814928266@s.whatsapp.net","copperingot":0},{"id":"6285251982627@s.whatsapp.net","copperingot":0},{"id":"6281282271664@s.whatsapp.net","copperingot":0},{"id":"918167286855@s.whatsapp.net","copperingot":0},{"id":"6287872755840@s.whatsapp.net","copperingot":14},{"id":"6285273570608@s.whatsapp.net","copperingot":0},{"id":"62895392032939@s.whatsapp.net","copperingot":0},{"id":"6285394303281@s.whatsapp.net","copperingot":0},{"id":"6283802471833@s.whatsapp.net","copperingot":0},{"id":"6281232133313@s.whatsapp.net","copperingot":0},{"id":"6282252937517@s.whatsapp.net","copperingot":0},{"id":"6288210246876@s.whatsapp.net","copperingot":0},{"id":"628811898629@s.whatsapp.net","copperingot":0},{"id":"6285813063915@s.whatsapp.net","copperingot":0},{"id":"6282368222677@s.whatsapp.net","copperingot":0},{"id":"6289630297223@s.whatsapp.net","copperingot":0},{"id":"6285695147239@s.whatsapp.net","copperingot":0},{"id":"6281281322703@s.whatsapp.net","copperingot":0},{"id":"628983100988@s.whatsapp.net","copperingot":0},{"id":"6285766330930@s.whatsapp.net","copperingot":0},{"id":"62895630335312@s.whatsapp.net","copperingot":0},{"id":"6281290985421@s.whatsapp.net","copperingot":0},{"id":"6281297710231@s.whatsapp.net","copperingot":0},{"id":"6289614426847@s.whatsapp.net","copperingot":0},{"id":"6281257113959@s.whatsapp.net","copperingot":0},{"id":"6282110052261@s.whatsapp.net","copperingot":0},{"id":"6282118823128@s.whatsapp.net","copperingot":0},{"id":"6289529923382@s.whatsapp.net","copperingot":0},{"id":"6289529467383@s.whatsapp.net","copperingot":0},{"id":"6282158381735@s.whatsapp.net","copperingot":0},{"id":"6283137027257@s.whatsapp.net","copperingot":0},{"id":"6287814085583@s.whatsapp.net","copperingot":0},{"id":"6281256623366@s.whatsapp.net","copperingot":0},{"id":"6289679070459@s.whatsapp.net","copperingot":0},{"id":"6281927152035@s.whatsapp.net","copperingot":0},{"id":"6288262741213@s.whatsapp.net","copperingot":0},{"id":"6282189766708@s.whatsapp.net","copperingot":0},{"id":"6288296335903@s.whatsapp.net","copperingot":0},{"id":"6283115217001@s.whatsapp.net","copperingot":0},{"id":"6283120882949@s.whatsapp.net","copperingot":0},{"id":"6289531852815@s.whatsapp.net","copperingot":0},{"id":"6285825005499@s.whatsapp.net","copperingot":0},{"id":"6285883401932@s.whatsapp.net","copperingot":0},{"id":"6287886829533@s.whatsapp.net","copperingot":0},{"id":"6281907274583@s.whatsapp.net","copperingot":0},{"id":"6287850639996@s.whatsapp.net","copperingot":0},{"id":"6285314688199@s.whatsapp.net","copperingot":0},{"id":"6282334926409@s.whatsapp.net","copperingot":0},{"id":"6283891606127@s.whatsapp.net","copperingot":0},{"id":"6285975360638@s.whatsapp.net","copperingot":0},{"id":"6281345534456@s.whatsapp.net","copperingot":0},{"id":"6281649056036@s.whatsapp.net","copperingot":0},{"id":"6282232074677@s.whatsapp.net","copperingot":0},{"id":"6285817610545@s.whatsapp.net","copperingot":0},{"id":"6285649472640@s.whatsapp.net","copperingot":0},{"id":"6283815795796@s.whatsapp.net","copperingot":0},{"id":"6285780530659@s.whatsapp.net","copperingot":0},{"id":"6281247883607@s.whatsapp.net","copperingot":0},{"id":"6285333260423@s.whatsapp.net","copperingot":0},{"id":"6288219428847@s.whatsapp.net","copperingot":0},{"id":"6285357055368@s.whatsapp.net","copperingot":0},{"id":"6285775215306@s.whatsapp.net","copperingot":0},{"id":"628872732758@s.whatsapp.net","copperingot":0},{"id":"6282273172107@s.whatsapp.net","copperingot":0},{"id":"6282292669854@s.whatsapp.net","copperingot":0},{"id":"6285320448024@s.whatsapp.net","copperingot":0},{"id":"6281803290532@s.whatsapp.net","copperingot":0},{"id":"6287866958539@s.whatsapp.net","copperingot":0},{"id":"994403434823@s.whatsapp.net","copperingot":0},{"id":"6288708344182@s.whatsapp.net","copperingot":20},{"id":"","copperingot":0},{"id":"79687569166@s.whatsapp.net","copperingot":0}]